osc_vad/__init__.py
osc_vad/fsmn.py
osc_vad/py.typed
osc_vad/utils.py
osc_vad/assets/fsmn/am.mvn
osc_vad/assets/fsmn/config.yaml
osc_vad/assets/fsmn/model.onnx
osc_vad-0.1.0.dist-info/METADATA
osc_vad-0.1.0.dist-info/WHEEL
osc_vad-0.1.0.dist-info/licenses/LICENSE
osc_vad-0.1.0.dist-info/RECORD
