Metadata-Version: 2.4
Name: osc-vad
Version: 0.1.0
Summary: Fast Voice Activity Detection Inference with Onnxruntime
Author-email: wangmengdi <790990241@qq.com>
License-File: LICENSE
Requires-Python: >=3.10
Requires-Dist: funasr-onnx>=0.4.1
Requires-Dist: loguru>=0.7.3
